pyemit/__init__.py
pyemit/emit.py
pyemit/remote.py
pyemit-0.5.0.dist-info/AUTHORS.rst
pyemit-0.5.0.dist-info/LICENSE
pyemit-0.5.0.dist-info/METADATA
pyemit-0.5.0.dist-info/WHEEL
pyemit-0.5.0.dist-info/top_level.txt
pyemit-0.5.0.dist-info/RECORD
