Metadata-Version: 2.1
Name: pyemit
Version: 0.5.0
Summary: 轻量级的异步消息通信，支持进程内消息通信，以及基于REDIS PUBSUB的远程消息。提供了进一步封装RPC的底层机制。
Home-page: https://github.com/hbaaron/pyemit
Author: Aaron Yang
Author-email: code@jieyu.ai
License: MIT license
Keywords: pyemit
Platform: UNKNOWN
Classifier: Development Status :: 2 - Pre-Alpha
Classifier: Intended Audience :: Developers
Classifier: License :: OSI Approved :: MIT License
Classifier: Natural Language :: English
Classifier: Programming Language :: Python :: 3.7
Classifier: Programming Language :: Python :: 3.8
Classifier: Programming Language :: Python :: 3.9
Requires-Python: >=3.7
License-File: LICENSE
License-File: AUTHORS.rst
Requires-Dist: aioredis (>=2.0.1)
